fabric_virt_tools/__init__.py
fabric_virt_tools/cpu_tune.py
fabric_virt_tools/numa_tune.py
fabric_virt_tools/utils.py
fabric_virt_tools/virt_tools_cli.py
fabric_virt_tools-1.0.0.dist-info/entry_points.txt
fabric_virt_tools-1.0.0.dist-info/LICENSE
fabric_virt_tools-1.0.0.dist-info/WHEEL
fabric_virt_tools-1.0.0.dist-info/METADATA
fabric_virt_tools-1.0.0.dist-info/RECORD
