Metadata-Version: 2.1
Name: fabric-virt-tools
Version: 1.0.0
Summary: Fabric Virtual Machine Tools
Keywords: Fabric Virtual Machine Tools
Author-email: Komal Thareja <kthare10@renci.org>
Requires-Python: >=3.6
Classifier: Programming Language :: Python :: 3
Classifier: License :: OSI Approved :: MIT License
Classifier: Operating System :: OS Independent
Requires-Dist: libvirt-python
Requires-Dist: psutil
Requires-Dist: click
Requires-Dist: pytest ; extra == "test"
Project-URL: Home, https://fabric-testbed.net/
Project-URL: Sources, https://github.com/fabric-testbed/VirtTools
Provides-Extra: test
